easyclone/__main__.py
easyclone/config.py
easyclone/main.py
easyclone/ipc/__init__.py
easyclone/ipc/client.py
easyclone/ipc/server.py
easyclone/rclone/__init__.py
easyclone/rclone/backup.py
easyclone/rclone/create_dirs.py
easyclone/rclone/operations.py
easyclone/shared/__init__.py
easyclone/shared/sync_status.py
easyclone/utils/__init__.py
easyclone/utils/essentials.py
easyclone/utils/path_manipulation.py
easyclone/utypes/__init__.py
easyclone/utypes/config.py
easyclone/utypes/enums.py
easyclone/utypes/models.py
easyclone-1.0.0.dist-info/licenses/LICENSE
easyclone-1.0.0.dist-info/METADATA
easyclone-1.0.0.dist-info/WHEEL
easyclone-1.0.0.dist-info/entry_points.txt
easyclone-1.0.0.dist-info/top_level.txt
easyclone-1.0.0.dist-info/RECORD
