Metadata-Version: 2.4
Name: easyclone
Version: 1.0.0
Summary: Very convenient Rclone bulk backup wrapper
Author-email: Ahmet Arda Kavakcı <ahmetardakavakci@gmail.com>
Maintainer-email: Ahmet Arda Kavakcı <ahmetardakavakci@gmail.com>
License-Expression: GPL-3.0-or-later
Project-URL: Repository, https://github.com/dybdeskarphet/easyclone
Project-URL: Documentation, https://github.com/dybdeskarphet/easyclone
Project-URL: Issues, https://github.com/dybdeskarphet/easyclone/issues
Project-URL: Changelog, https://github.com/dybdeskarphet/easyclone/blob/main/CHANGELOG.md
Keywords: backup,sync,google,drive,easyclone
Requires-Python: >=3.13
License-File: LICENSE
Requires-Dist: pydantic>=2.11.5
Requires-Dist: toml>=0.10.2
Requires-Dist: typer>=0.16.0
Dynamic: license-file
